requests_selenium/__init__.py
requests_selenium/tempCodeRunnerFile.py
requests_selenium/utils.py
requests_selenium-0.0.7.dist-info/METADATA
requests_selenium-0.0.7.dist-info/WHEEL
requests_selenium-0.0.7.dist-info/top_level.txt
requests_selenium-0.0.7.dist-info/RECORD
