Metadata-Version: 2.1
Name: requests-selenium
Version: 0.0.7
Summary: A Python package for fetching page source using Selenium
Author: Ben Bavonese
Classifier: Development Status :: 4 - Beta
Classifier: Intended Audience :: Developers
Classifier: License :: OSI Approved :: MIT License
Classifier: Programming Language :: Python
Classifier: Programming Language :: Python :: 3
Classifier: Programming Language :: Python :: 3.6
Classifier: Programming Language :: Python :: 3.7
Classifier: Programming Language :: Python :: 3.8
Classifier: Programming Language :: Python :: 3.9
Classifier: Programming Language :: Python :: 3.10
Classifier: Programming Language :: Python :: 3.11
Requires-Dist: requests
Requires-Dist: beautifulsoup4
Requires-Dist: chromedriver-autoinstaller
Requires-Dist: selenium
